[{"ANNO":2024,"TOTALE":14,"TIPO SOGGETTO":"AIRE","STATO DI LAVORAZIONE":"ACCOLTA","MESE":9},{"ANNO":2024,"TOTALE":23177,"TIPO SOGGETTO":"Residenti","STATO DI LAVORAZIONE":"ACCOLTA","MESE":9},{"ANNO":2024,"TOTALE":15,"TIPO SOGGETTO":"AIRE","STATO DI LAVORAZIONE":"ANNULLATA","MESE":9},{"ANNO":2024,"TOTALE":915,"TIPO SOGGETTO":"Residenti","STATO DI LAVORAZIONE":"ANNULLATA","MESE":9},{"ANNO":2024,"TOTALE":135,"TIPO SOGGETTO":"AIRE","STATO DI LAVORAZIONE":"IN LAVORAZIONE","MESE":9},{"ANNO":2024,"TOTALE":24512,"TIPO SOGGETTO":"Residenti","STATO DI LAVORAZIONE":"IN LAVORAZIONE","MESE":9},{"ANNO":2024,"TOTALE":47,"TIPO SOGGETTO":"AIRE","STATO DI LAVORAZIONE":"IRRICEVIBILE","MESE":9},{"ANNO":2024,"TOTALE":3845,"TIPO SOGGETTO":"Residenti","STATO DI LAVORAZIONE":"IRRICEVIBILE","MESE":9}]