[{"ANNO":2026,"STATO_DI_LAVORAZIONE":"ACCOLTA","TOTALE":11,"TIPO_SOGGETTO":"AIRE","MESE":2},{"ANNO":2026,"STATO_DI_LAVORAZIONE":"ACCOLTA","TOTALE":28913,"TIPO_SOGGETTO":"Residenti","MESE":2},{"ANNO":2026,"STATO_DI_LAVORAZIONE":"ANNULLATA","TOTALE":19,"TIPO_SOGGETTO":"AIRE","MESE":2},{"ANNO":2026,"STATO_DI_LAVORAZIONE":"ANNULLATA","TOTALE":985,"TIPO_SOGGETTO":"Residenti","MESE":2},{"ANNO":2026,"STATO_DI_LAVORAZIONE":"IN LAVORAZIONE","TOTALE":138,"TIPO_SOGGETTO":"AIRE","MESE":2},{"ANNO":2026,"STATO_DI_LAVORAZIONE":"IN LAVORAZIONE","TOTALE":31493,"TIPO_SOGGETTO":"Residenti","MESE":2},{"ANNO":2026,"STATO_DI_LAVORAZIONE":"IRRICEVIBILE","TOTALE":80,"TIPO_SOGGETTO":"AIRE","MESE":2},{"ANNO":2026,"STATO_DI_LAVORAZIONE":"IRRICEVIBILE","TOTALE":5795,"TIPO_SOGGETTO":"Residenti","MESE":2}]