[{"ANNO":2023,"BOLLO":15,"TOTALE":94,"TIPO SOGGETTO":"AIRE","TIPOLOGIA CERTIFICATO":"CITTADINANZA","ESENTI DA BOLLO":79,"MESE":12},{"ANNO":2023,"BOLLO":94,"TOTALE":447,"TIPO SOGGETTO":"AIRE","TIPOLOGIA CERTIFICATO":"CONTESTUALE","ESENTI DA BOLLO":353,"MESE":12},{"ANNO":2023,"BOLLO":0,"TOTALE":2,"TIPO SOGGETTO":"AIRE","TIPOLOGIA CERTIFICATO":"ESISTENZA IN VITA","ESENTI DA BOLLO":2,"MESE":12},{"ANNO":2023,"BOLLO":22,"TOTALE":146,"TIPO SOGGETTO":"AIRE","TIPOLOGIA CERTIFICATO":"MATRIMONIO","ESENTI DA BOLLO":124,"MESE":12},{"ANNO":2023,"BOLLO":79,"TOTALE":309,"TIPO SOGGETTO":"AIRE","TIPOLOGIA CERTIFICATO":"NASCITA","ESENTI DA BOLLO":230,"MESE":12},{"ANNO":2023,"BOLLO":73,"TOTALE":581,"TIPO SOGGETTO":"AIRE","TIPOLOGIA CERTIFICATO":"RESIDENZA","ESENTI DA BOLLO":508,"MESE":12},{"ANNO":2023,"BOLLO":0,"TOTALE":2,"TIPO SOGGETTO":"AIRE","TIPOLOGIA CERTIFICATO":"STATO CIVILE","ESENTI DA BOLLO":2,"MESE":12},{"ANNO":2023,"BOLLO":23,"TOTALE":210,"TIPO SOGGETTO":"AIRE","TIPOLOGIA CERTIFICATO":"STATO FAMIGLIA","ESENTI DA BOLLO":187,"MESE":12},{"ANNO":2023,"BOLLO":0,"TOTALE":1,"TIPO SOGGETTO":"AIRE","TIPOLOGIA CERTIFICATO":"STATO FAMIGLIA E STATO CIVILE","ESENTI DA BOLLO":1,"MESE":12},{"ANNO":2023,"BOLLO":1,"TOTALE":1,"TIPO SOGGETTO":"AIRE","TIPOLOGIA CERTIFICATO":"UNIONE CIVILE ","ESENTI DA BOLLO":0,"MESE":12},{"ANNO":2023,"BOLLO":78,"TOTALE":1601,"TIPO SOGGETTO":"Residenti","TIPOLOGIA CERTIFICATO":"CITTADINANZA","ESENTI DA BOLLO":1523,"MESE":12},{"ANNO":2023,"BOLLO":6666,"TOTALE":58740,"TIPO SOGGETTO":"Residenti","TIPOLOGIA CERTIFICATO":"CONTESTUALE","ESENTI DA BOLLO":52074,"MESE":12},{"ANNO":2023,"BOLLO":2,"TOTALE":11,"TIPO SOGGETTO":"Residenti","TIPOLOGIA CERTIFICATO":"CONTRATTO CONVIVENZA","ESENTI DA BOLLO":9,"MESE":12},{"ANNO":2023,"BOLLO":137,"TOTALE":2081,"TIPO SOGGETTO":"Residenti","TIPOLOGIA CERTIFICATO":"ESISTENZA IN VITA","ESENTI DA BOLLO":1944,"MESE":12},{"ANNO":2023,"BOLLO":868,"TOTALE":10352,"TIPO SOGGETTO":"Residenti","TIPOLOGIA CERTIFICATO":"MATRIMONIO","ESENTI DA BOLLO":9484,"MESE":12},{"ANNO":2023,"BOLLO":1026,"TOTALE":11255,"TIPO SOGGETTO":"Residenti","TIPOLOGIA CERTIFICATO":"NASCITA","ESENTI DA BOLLO":10229,"MESE":12},{"ANNO":2023,"BOLLO":3619,"TOTALE":109640,"TIPO SOGGETTO":"Residenti","TIPOLOGIA CERTIFICATO":"RESIDENZA","ESENTI DA BOLLO":106021,"MESE":12},{"ANNO":2023,"BOLLO":0,"TOTALE":56,"TIPO SOGGETTO":"Residenti","TIPOLOGIA CERTIFICATO":"RESIDENZA IN CONVIVENZA","ESENTI DA BOLLO":56,"MESE":12},{"ANNO":2023,"BOLLO":1412,"TOTALE":10103,"TIPO SOGGETTO":"Residenti","TIPOLOGIA CERTIFICATO":"STATO CIVILE","ESENTI DA BOLLO":8691,"MESE":12},{"ANNO":2023,"BOLLO":3839,"TOTALE":46107,"TIPO SOGGETTO":"Residenti","TIPOLOGIA CERTIFICATO":"STATO FAMIGLIA","ESENTI DA BOLLO":42268,"MESE":12},{"ANNO":2023,"BOLLO":590,"TOTALE":7479,"TIPO SOGGETTO":"Residenti","TIPOLOGIA CERTIFICATO":"STATO FAMIGLIA CON RAPPORTI PARENTELA","ESENTI DA BOLLO":6889,"MESE":12},{"ANNO":2023,"BOLLO":550,"TOTALE":6136,"TIPO SOGGETTO":"Residenti","TIPOLOGIA CERTIFICATO":"STATO FAMIGLIA E STATO CIVILE","ESENTI DA BOLLO":5586,"MESE":12},{"ANNO":2023,"BOLLO":1528,"TOTALE":4864,"TIPO SOGGETTO":"Residenti","TIPOLOGIA CERTIFICATO":"STATO LIBERO","ESENTI DA BOLLO":3336,"MESE":12},{"ANNO":2023,"BOLLO":7,"TOTALE":53,"TIPO SOGGETTO":"Residenti","TIPOLOGIA CERTIFICATO":"UNIONE CIVILE ","ESENTI DA BOLLO":46,"MESE":12}]