[{"ANNO":2025,"TOTALE":6635,"MESE":2},{"ANNO":2025,"TOTALE":9139,"MESE":1},{"ANNO":2024,"TOTALE":5069,"MESE":12},{"ANNO":2024,"TOTALE":6862,"MESE":11},{"ANNO":2024,"TOTALE":9178,"MESE":10},{"ANNO":2024,"TOTALE":9408,"MESE":9},{"ANNO":2024,"TOTALE":4743,"MESE":8},{"ANNO":2024,"TOTALE":7256,"MESE":7},{"ANNO":2024,"TOTALE":6090,"MESE":6},{"ANNO":2024,"TOTALE":7077,"MESE":5},{"ANNO":2024,"TOTALE":6482,"MESE":4},{"ANNO":2024,"TOTALE":6588,"MESE":3},{"ANNO":2024,"TOTALE":7420,"MESE":2},{"ANNO":2024,"TOTALE":8071,"MESE":1},{"ANNO":2023,"TOTALE":4179,"MESE":12},{"ANNO":2023,"TOTALE":6365,"MESE":11},{"ANNO":2023,"TOTALE":8075,"MESE":10},{"ANNO":2023,"TOTALE":8877,"MESE":9},{"ANNO":2023,"TOTALE":4420,"MESE":8},{"ANNO":2023,"TOTALE":6261,"MESE":7},{"ANNO":2023,"TOTALE":5644,"MESE":6},{"ANNO":2023,"TOTALE":6419,"MESE":5},{"ANNO":2023,"TOTALE":5444,"MESE":4},{"ANNO":2023,"TOTALE":7095,"MESE":3},{"ANNO":2023,"TOTALE":7803,"MESE":2},{"ANNO":2023,"TOTALE":9371,"MESE":1},{"ANNO":2022,"TOTALE":5647,"MESE":12},{"ANNO":2022,"TOTALE":7447,"MESE":11},{"ANNO":2022,"TOTALE":8505,"MESE":10},{"ANNO":2022,"TOTALE":8939,"MESE":9},{"ANNO":2022,"TOTALE":4423,"MESE":8},{"ANNO":2022,"TOTALE":6177,"MESE":7},{"ANNO":2022,"TOTALE":6084,"MESE":6},{"ANNO":2022,"TOTALE":6649,"MESE":5},{"ANNO":2022,"TOTALE":5571,"MESE":4},{"ANNO":2022,"TOTALE":6867,"MESE":3},{"ANNO":2022,"TOTALE":7013,"MESE":2},{"ANNO":2022,"TOTALE":7252,"MESE":1},{"ANNO":2021,"TOTALE":4899,"MESE":12},{"ANNO":2021,"TOTALE":6169,"MESE":11}]