[{"ANNO":2024,"BOLLO":0,"TOTALE":1,"TIPO SOGGETTO":"AIRE","TIPOLOGIA CERTIFICATO":"CITTADINANZA","ESENTI DA BOLLO":1,"MESE":5},{"ANNO":2024,"BOLLO":2,"TOTALE":17,"TIPO SOGGETTO":"AIRE","TIPOLOGIA CERTIFICATO":"CONTESTUALE","ESENTI DA BOLLO":15,"MESE":5},{"ANNO":2024,"BOLLO":0,"TOTALE":1,"TIPO SOGGETTO":"AIRE","TIPOLOGIA CERTIFICATO":"ISCRIZIONE NELLE LISTE ELETTORALI","ESENTI DA BOLLO":1,"MESE":5},{"ANNO":2024,"BOLLO":1,"TOTALE":4,"TIPO SOGGETTO":"AIRE","TIPOLOGIA CERTIFICATO":"MATRIMONIO","ESENTI DA BOLLO":3,"MESE":5},{"ANNO":2024,"BOLLO":1,"TOTALE":7,"TIPO SOGGETTO":"AIRE","TIPOLOGIA CERTIFICATO":"NASCITA","ESENTI DA BOLLO":6,"MESE":5},{"ANNO":2024,"BOLLO":3,"TOTALE":17,"TIPO SOGGETTO":"AIRE","TIPOLOGIA CERTIFICATO":"RESIDENZA","ESENTI DA BOLLO":14,"MESE":5},{"ANNO":2024,"BOLLO":0,"TOTALE":8,"TIPO SOGGETTO":"AIRE","TIPOLOGIA CERTIFICATO":"STATO FAMIGLIA","ESENTI DA BOLLO":8,"MESE":5},{"ANNO":2024,"BOLLO":3,"TOTALE":72,"TIPO SOGGETTO":"Residenti","TIPOLOGIA CERTIFICATO":"CITTADINANZA","ESENTI DA BOLLO":69,"MESE":5},{"ANNO":2024,"BOLLO":311,"TOTALE":2027,"TIPO SOGGETTO":"Residenti","TIPOLOGIA CERTIFICATO":"CONTESTUALE","ESENTI DA BOLLO":1716,"MESE":5},{"ANNO":2024,"BOLLO":3,"TOTALE":63,"TIPO SOGGETTO":"Residenti","TIPOLOGIA CERTIFICATO":"ESISTENZA IN VITA","ESENTI DA BOLLO":60,"MESE":5},{"ANNO":2024,"BOLLO":1,"TOTALE":41,"TIPO SOGGETTO":"Residenti","TIPOLOGIA CERTIFICATO":"GODIMENTO DEI DIRITTI POLITICI","ESENTI DA BOLLO":40,"MESE":5},{"ANNO":2024,"BOLLO":2,"TOTALE":503,"TIPO SOGGETTO":"Residenti","TIPOLOGIA CERTIFICATO":"ISCRIZIONE NELLE LISTE ELETTORALI","ESENTI DA BOLLO":501,"MESE":5},{"ANNO":2024,"BOLLO":26,"TOTALE":287,"TIPO SOGGETTO":"Residenti","TIPOLOGIA CERTIFICATO":"MATRIMONIO","ESENTI DA BOLLO":261,"MESE":5},{"ANNO":2024,"BOLLO":38,"TOTALE":429,"TIPO SOGGETTO":"Residenti","TIPOLOGIA CERTIFICATO":"NASCITA","ESENTI DA BOLLO":391,"MESE":5},{"ANNO":2024,"BOLLO":82,"TOTALE":2522,"TIPO SOGGETTO":"Residenti","TIPOLOGIA CERTIFICATO":"RESIDENZA","ESENTI DA BOLLO":2440,"MESE":5},{"ANNO":2024,"BOLLO":0,"TOTALE":1,"TIPO SOGGETTO":"Residenti","TIPOLOGIA CERTIFICATO":"RESIDENZA IN CONVIVENZA","ESENTI DA BOLLO":1,"MESE":5},{"ANNO":2024,"BOLLO":49,"TOTALE":295,"TIPO SOGGETTO":"Residenti","TIPOLOGIA CERTIFICATO":"STATO CIVILE","ESENTI DA BOLLO":246,"MESE":5},{"ANNO":2024,"BOLLO":130,"TOTALE":1169,"TIPO SOGGETTO":"Residenti","TIPOLOGIA CERTIFICATO":"STATO FAMIGLIA","ESENTI DA BOLLO":1039,"MESE":5},{"ANNO":2024,"BOLLO":16,"TOTALE":179,"TIPO SOGGETTO":"Residenti","TIPOLOGIA CERTIFICATO":"STATO FAMIGLIA CON RAPPORTI PARENTELA","ESENTI DA BOLLO":163,"MESE":5},{"ANNO":2024,"BOLLO":24,"TOTALE":167,"TIPO SOGGETTO":"Residenti","TIPOLOGIA CERTIFICATO":"STATO FAMIGLIA E STATO CIVILE","ESENTI DA BOLLO":143,"MESE":5},{"ANNO":2024,"BOLLO":40,"TOTALE":112,"TIPO SOGGETTO":"Residenti","TIPOLOGIA CERTIFICATO":"STATO LIBERO","ESENTI DA BOLLO":72,"MESE":5}]