[{"ANNO":2026,"TIPOLOGIA_CERTIFICATO":"CITTADINANZA","BOLLO":3,"ESENTI_DA_BOLLO":18,"TOTALE":21,"TIPO_SOGGETTO":"AIRE","MESE":1},{"ANNO":2026,"TIPOLOGIA_CERTIFICATO":"CONTESTUALE","BOLLO":20,"ESENTI_DA_BOLLO":71,"TOTALE":91,"TIPO_SOGGETTO":"AIRE","MESE":1},{"ANNO":2026,"TIPOLOGIA_CERTIFICATO":"MATRIMONIO","BOLLO":5,"ESENTI_DA_BOLLO":26,"TOTALE":31,"TIPO_SOGGETTO":"AIRE","MESE":1},{"ANNO":2026,"TIPOLOGIA_CERTIFICATO":"NASCITA","BOLLO":48,"ESENTI_DA_BOLLO":54,"TOTALE":102,"TIPO_SOGGETTO":"AIRE","MESE":1},{"ANNO":2026,"TIPOLOGIA_CERTIFICATO":"RESIDENZA","BOLLO":25,"ESENTI_DA_BOLLO":89,"TOTALE":114,"TIPO_SOGGETTO":"AIRE","MESE":1},{"ANNO":2026,"TIPOLOGIA_CERTIFICATO":"STATO FAMIGLIA","BOLLO":6,"ESENTI_DA_BOLLO":43,"TOTALE":49,"TIPO_SOGGETTO":"AIRE","MESE":1},{"ANNO":2026,"TIPOLOGIA_CERTIFICATO":"CITTADINANZA","BOLLO":19,"ESENTI_DA_BOLLO":245,"TOTALE":264,"TIPO_SOGGETTO":"Residenti","MESE":1},{"ANNO":2026,"TIPOLOGIA_CERTIFICATO":"CONTESTUALE","BOLLO":1402,"ESENTI_DA_BOLLO":11176,"TOTALE":12578,"TIPO_SOGGETTO":"Residenti","MESE":1},{"ANNO":2026,"TIPOLOGIA_CERTIFICATO":"CONTRATTO CONVIVENZA","BOLLO":1,"ESENTI_DA_BOLLO":0,"TOTALE":1,"TIPO_SOGGETTO":"Residenti","MESE":1},{"ANNO":2026,"TIPOLOGIA_CERTIFICATO":"ESISTENZA IN VITA","BOLLO":38,"ESENTI_DA_BOLLO":470,"TOTALE":508,"TIPO_SOGGETTO":"Residenti","MESE":1},{"ANNO":2026,"TIPOLOGIA_CERTIFICATO":"GODIMENTO DEI DIRITTI POLITICI","BOLLO":8,"ESENTI_DA_BOLLO":18,"TOTALE":26,"TIPO_SOGGETTO":"Residenti","MESE":1},{"ANNO":2026,"TIPOLOGIA_CERTIFICATO":"ISCRIZIONE NELLE LISTE ELETTORALI","BOLLO":3,"ESENTI_DA_BOLLO":42,"TOTALE":45,"TIPO_SOGGETTO":"Residenti","MESE":1},{"ANNO":2026,"TIPOLOGIA_CERTIFICATO":"MATRIMONIO","BOLLO":157,"ESENTI_DA_BOLLO":1320,"TOTALE":1477,"TIPO_SOGGETTO":"Residenti","MESE":1},{"ANNO":2026,"TIPOLOGIA_CERTIFICATO":"NASCITA","BOLLO":350,"ESENTI_DA_BOLLO":2002,"TOTALE":2352,"TIPO_SOGGETTO":"Residenti","MESE":1},{"ANNO":2026,"TIPOLOGIA_CERTIFICATO":"RESIDENZA","BOLLO":943,"ESENTI_DA_BOLLO":19797,"TOTALE":20740,"TIPO_SOGGETTO":"Residenti","MESE":1},{"ANNO":2026,"TIPOLOGIA_CERTIFICATO":"RESIDENZA IN CONVIVENZA","BOLLO":0,"ESENTI_DA_BOLLO":20,"TOTALE":20,"TIPO_SOGGETTO":"Residenti","MESE":1},{"ANNO":2026,"TIPOLOGIA_CERTIFICATO":"STATO CIVILE","BOLLO":155,"ESENTI_DA_BOLLO":1144,"TOTALE":1299,"TIPO_SOGGETTO":"Residenti","MESE":1},{"ANNO":2026,"TIPOLOGIA_CERTIFICATO":"STATO FAMIGLIA","BOLLO":917,"ESENTI_DA_BOLLO":10342,"TOTALE":11259,"TIPO_SOGGETTO":"Residenti","MESE":1},{"ANNO":2026,"TIPOLOGIA_CERTIFICATO":"STATO FAMIGLIA CON RAPPORTI PARENTELA","BOLLO":94,"ESENTI_DA_BOLLO":1376,"TOTALE":1470,"TIPO_SOGGETTO":"Residenti","MESE":1},{"ANNO":2026,"TIPOLOGIA_CERTIFICATO":"STATO FAMIGLIA E STATO CIVILE","BOLLO":86,"ESENTI_DA_BOLLO":915,"TOTALE":1001,"TIPO_SOGGETTO":"Residenti","MESE":1},{"ANNO":2026,"TIPOLOGIA_CERTIFICATO":"STATO LIBERO","BOLLO":184,"ESENTI_DA_BOLLO":253,"TOTALE":437,"TIPO_SOGGETTO":"Residenti","MESE":1},{"ANNO":2026,"TIPOLOGIA_CERTIFICATO":"UNIONE CIVILE ","BOLLO":2,"ESENTI_DA_BOLLO":6,"TOTALE":8,"TIPO_SOGGETTO":"Residenti","MESE":1}]