[{"ANNO":2022,"TOTALE":8609,"TIPOLOGIA":"ESPATRI","TIPO_SOGGETTO":"AIRE","MESE":2},{"ANNO":2022,"TOTALE":22484,"TIPOLOGIA":"ESTERO CON ESTERO","TIPO_SOGGETTO":"AIRE","MESE":2},{"ANNO":2022,"TOTALE":1401,"TIPOLOGIA":"RIENTRI AIRE","TIPO_SOGGETTO":"AIRE","MESE":2},{"ANNO":2022,"TOTALE":34833,"TIPOLOGIA":"DIVERSA REGIONE","TIPO_SOGGETTO":"Residenti","MESE":2},{"ANNO":2022,"TOTALE":635,"TIPOLOGIA":"ESPATRI","TIPO_SOGGETTO":"Residenti","MESE":2},{"ANNO":2022,"TOTALE":6933,"TIPOLOGIA":"RIENTRI AIRE","TIPO_SOGGETTO":"Residenti","MESE":2},{"ANNO":2022,"TOTALE":110888,"TIPOLOGIA":"STESSA REGIONE","TIPO_SOGGETTO":"Residenti","MESE":2},{"ANNO":2022,"TOTALE":168677,"TIPOLOGIA":"STESSO COMUNE","TIPO_SOGGETTO":"Residenti","MESE":2},{"ANNO":2022,"TOTALE":9664,"TIPOLOGIA":"ESPATRI","TIPO_SOGGETTO":"AIRE","MESE":3},{"ANNO":2022,"TOTALE":26888,"TIPOLOGIA":"ESTERO CON ESTERO","TIPO_SOGGETTO":"AIRE","MESE":3},{"ANNO":2022,"TOTALE":1739,"TIPOLOGIA":"RIENTRI AIRE","TIPO_SOGGETTO":"AIRE","MESE":3},{"ANNO":2022,"TOTALE":38186,"TIPOLOGIA":"DIVERSA REGIONE","TIPO_SOGGETTO":"Residenti","MESE":3},{"ANNO":2022,"TOTALE":711,"TIPOLOGIA":"ESPATRI","TIPO_SOGGETTO":"Residenti","MESE":3},{"ANNO":2022,"TOTALE":7624,"TIPOLOGIA":"RIENTRI AIRE","TIPO_SOGGETTO":"Residenti","MESE":3},{"ANNO":2022,"TOTALE":121156,"TIPOLOGIA":"STESSA REGIONE","TIPO_SOGGETTO":"Residenti","MESE":3},{"ANNO":2022,"TOTALE":185744,"TIPOLOGIA":"STESSO COMUNE","TIPO_SOGGETTO":"Residenti","MESE":3},{"ANNO":2022,"TOTALE":7668,"TIPOLOGIA":"ESPATRI","TIPO_SOGGETTO":"AIRE","MESE":4},{"ANNO":2022,"TOTALE":22365,"TIPOLOGIA":"ESTERO CON ESTERO","TIPO_SOGGETTO":"AIRE","MESE":4},{"ANNO":2022,"TOTALE":1596,"TIPOLOGIA":"RIENTRI AIRE","TIPO_SOGGETTO":"AIRE","MESE":4},{"ANNO":2022,"TOTALE":30408,"TIPOLOGIA":"DIVERSA REGIONE","TIPO_SOGGETTO":"Residenti","MESE":4},{"ANNO":2022,"TOTALE":538,"TIPOLOGIA":"ESPATRI","TIPO_SOGGETTO":"Residenti","MESE":4},{"ANNO":2022,"TOTALE":6338,"TIPOLOGIA":"RIENTRI AIRE","TIPO_SOGGETTO":"Residenti","MESE":4},{"ANNO":2022,"TOTALE":110413,"TIPOLOGIA":"STESSA REGIONE","TIPO_SOGGETTO":"Residenti","MESE":4},{"ANNO":2022,"TOTALE":147213,"TIPOLOGIA":"STESSO COMUNE","TIPO_SOGGETTO":"Residenti","MESE":4},{"ANNO":2022,"TOTALE":7296,"TIPOLOGIA":"ESPATRI","TIPO_SOGGETTO":"AIRE","MESE":5},{"ANNO":2022,"TOTALE":25250,"TIPOLOGIA":"ESTERO CON ESTERO","TIPO_SOGGETTO":"AIRE","MESE":5},{"ANNO":2022,"TOTALE":1834,"TIPOLOGIA":"RIENTRI AIRE","TIPO_SOGGETTO":"AIRE","MESE":5},{"ANNO":2022,"TOTALE":35859,"TIPOLOGIA":"DIVERSA REGIONE","TIPO_SOGGETTO":"Residenti","MESE":5},{"ANNO":2022,"TOTALE":595,"TIPOLOGIA":"ESPATRI","TIPO_SOGGETTO":"Residenti","MESE":5},{"ANNO":2022,"TOTALE":7790,"TIPOLOGIA":"RIENTRI AIRE","TIPO_SOGGETTO":"Residenti","MESE":5},{"ANNO":2022,"TOTALE":119453,"TIPOLOGIA":"STESSA REGIONE","TIPO_SOGGETTO":"Residenti","MESE":5},{"ANNO":2022,"TOTALE":178323,"TIPOLOGIA":"STESSO COMUNE","TIPO_SOGGETTO":"Residenti","MESE":5},{"ANNO":2022,"TOTALE":6781,"TIPOLOGIA":"ESPATRI","TIPO_SOGGETTO":"AIRE","MESE":6},{"ANNO":2022,"TOTALE":21539,"TIPOLOGIA":"ESTERO CON ESTERO","TIPO_SOGGETTO":"AIRE","MESE":6},{"ANNO":2022,"TOTALE":1849,"TIPOLOGIA":"RIENTRI AIRE","TIPO_SOGGETTO":"AIRE","MESE":6},{"ANNO":2022,"TOTALE":34741,"TIPOLOGIA":"DIVERSA REGIONE","TIPO_SOGGETTO":"Residenti","MESE":6},{"ANNO":2022,"TOTALE":466,"TIPOLOGIA":"ESPATRI","TIPO_SOGGETTO":"Residenti","MESE":6},{"ANNO":2022,"TOTALE":7416,"TIPOLOGIA":"RIENTRI AIRE","TIPO_SOGGETTO":"Residenti","MESE":6},{"ANNO":2022,"TOTALE":115068,"TIPOLOGIA":"STESSA REGIONE","TIPO_SOGGETTO":"Residenti","MESE":6},{"ANNO":2022,"TOTALE":158474,"TIPOLOGIA":"STESSO COMUNE","TIPO_SOGGETTO":"Residenti","MESE":6},{"ANNO":2022,"TOTALE":7656,"TIPOLOGIA":"ESPATRI","TIPO_SOGGETTO":"AIRE","MESE":7},{"ANNO":2022,"TOTALE":22591,"TIPOLOGIA":"ESTERO CON ESTERO","TIPO_SOGGETTO":"AIRE","MESE":7},{"ANNO":2022,"TOTALE":2034,"TIPOLOGIA":"RIENTRI AIRE","TIPO_SOGGETTO":"AIRE","MESE":7},{"ANNO":2022,"TOTALE":36953,"TIPOLOGIA":"DIVERSA REGIONE","TIPO_SOGGETTO":"Residenti","MESE":7},{"ANNO":2022,"TOTALE":508,"TIPOLOGIA":"ESPATRI","TIPO_SOGGETTO":"Residenti","MESE":7},{"ANNO":2022,"TOTALE":7894,"TIPOLOGIA":"RIENTRI AIRE","TIPO_SOGGETTO":"Residenti","MESE":7},{"ANNO":2022,"TOTALE":115582,"TIPOLOGIA":"STESSA REGIONE","TIPO_SOGGETTO":"Residenti","MESE":7},{"ANNO":2022,"TOTALE":151994,"TIPOLOGIA":"STESSO COMUNE","TIPO_SOGGETTO":"Residenti","MESE":7},{"ANNO":2022,"TOTALE":7906,"TIPOLOGIA":"ESPATRI","TIPO_SOGGETTO":"AIRE","MESE":8},{"ANNO":2022,"TOTALE":38796,"TIPOLOGIA":"ESTERO CON ESTERO","TIPO_SOGGETTO":"AIRE","MESE":8},{"ANNO":2022,"TOTALE":2268,"TIPOLOGIA":"RIENTRI AIRE","TIPO_SOGGETTO":"AIRE","MESE":8},{"ANNO":2022,"TOTALE":39256,"TIPOLOGIA":"DIVERSA REGIONE","TIPO_SOGGETTO":"Residenti","MESE":8},{"ANNO":2022,"TOTALE":525,"TIPOLOGIA":"ESPATRI","TIPO_SOGGETTO":"Residenti","MESE":8},{"ANNO":2022,"TOTALE":8003,"TIPOLOGIA":"RIENTRI AIRE","TIPO_SOGGETTO":"Residenti","MESE":8},{"ANNO":2022,"TOTALE":112696,"TIPOLOGIA":"STESSA REGIONE","TIPO_SOGGETTO":"Residenti","MESE":8},{"ANNO":2022,"TOTALE":143700,"TIPOLOGIA":"STESSO COMUNE","TIPO_SOGGETTO":"Residenti","MESE":8},{"ANNO":2022,"TOTALE":6917,"TIPOLOGIA":"ESPATRI","TIPO_SOGGETTO":"AIRE","MESE":9},{"ANNO":2022,"TOTALE":25798,"TIPOLOGIA":"ESTERO CON ESTERO","TIPO_SOGGETTO":"AIRE","MESE":9},{"ANNO":2022,"TOTALE":2040,"TIPOLOGIA":"RIENTRI AIRE","TIPO_SOGGETTO":"AIRE","MESE":9},{"ANNO":2022,"TOTALE":45808,"TIPOLOGIA":"DIVERSA REGIONE","TIPO_SOGGETTO":"Residenti","MESE":9},{"ANNO":2022,"TOTALE":497,"TIPOLOGIA":"ESPATRI","TIPO_SOGGETTO":"Residenti","MESE":9},{"ANNO":2022,"TOTALE":8806,"TIPOLOGIA":"RIENTRI AIRE","TIPO_SOGGETTO":"Residenti","MESE":9},{"ANNO":2022,"TOTALE":115069,"TIPOLOGIA":"STESSA REGIONE","TIPO_SOGGETTO":"Residenti","MESE":9},{"ANNO":2022,"TOTALE":155857,"TIPOLOGIA":"STESSO COMUNE","TIPO_SOGGETTO":"Residenti","MESE":9},{"ANNO":2022,"TOTALE":7939,"TIPOLOGIA":"ESPATRI","TIPO_SOGGETTO":"AIRE","MESE":10},{"ANNO":2022,"TOTALE":27859,"TIPOLOGIA":"ESTERO CON ESTERO","TIPO_SOGGETTO":"AIRE","MESE":10},{"ANNO":2022,"TOTALE":1793,"TIPOLOGIA":"RIENTRI AIRE","TIPO_SOGGETTO":"AIRE","MESE":10},{"ANNO":2022,"TOTALE":43504,"TIPOLOGIA":"DIVERSA REGIONE","TIPO_SOGGETTO":"Residenti","MESE":10},{"ANNO":2022,"TOTALE":667,"TIPOLOGIA":"ESPATRI","TIPO_SOGGETTO":"Residenti","MESE":10},{"ANNO":2022,"TOTALE":8469,"TIPOLOGIA":"RIENTRI AIRE","TIPO_SOGGETTO":"Residenti","MESE":10},{"ANNO":2022,"TOTALE":123432,"TIPOLOGIA":"STESSA REGIONE","TIPO_SOGGETTO":"Residenti","MESE":10},{"ANNO":2022,"TOTALE":168863,"TIPOLOGIA":"STESSO COMUNE","TIPO_SOGGETTO":"Residenti","MESE":10},{"ANNO":2022,"TOTALE":9396,"TIPOLOGIA":"ESPATRI","TIPO_SOGGETTO":"AIRE","MESE":11},{"ANNO":2022,"TOTALE":27965,"TIPOLOGIA":"ESTERO CON ESTERO","TIPO_SOGGETTO":"AIRE","MESE":11},{"ANNO":2022,"TOTALE":1605,"TIPOLOGIA":"RIENTRI AIRE","TIPO_SOGGETTO":"AIRE","MESE":11},{"ANNO":2022,"TOTALE":40199,"TIPOLOGIA":"DIVERSA REGIONE","TIPO_SOGGETTO":"Residenti","MESE":11},{"ANNO":2022,"TOTALE":720,"TIPOLOGIA":"ESPATRI","TIPO_SOGGETTO":"Residenti","MESE":11},{"ANNO":2022,"TOTALE":7893,"TIPOLOGIA":"RIENTRI AIRE","TIPO_SOGGETTO":"Residenti","MESE":11},{"ANNO":2022,"TOTALE":119957,"TIPOLOGIA":"STESSA REGIONE","TIPO_SOGGETTO":"Residenti","MESE":11},{"ANNO":2022,"TOTALE":175968,"TIPOLOGIA":"STESSO COMUNE","TIPO_SOGGETTO":"Residenti","MESE":11},{"ANNO":2022,"TOTALE":8566,"TIPOLOGIA":"ESPATRI","TIPO_SOGGETTO":"AIRE","MESE":12},{"ANNO":2022,"TOTALE":23477,"TIPOLOGIA":"ESTERO CON ESTERO","TIPO_SOGGETTO":"AIRE","MESE":12},{"ANNO":2022,"TOTALE":1532,"TIPOLOGIA":"RIENTRI AIRE","TIPO_SOGGETTO":"AIRE","MESE":12},{"ANNO":2022,"TOTALE":33152,"TIPOLOGIA":"DIVERSA REGIONE","TIPO_SOGGETTO":"Residenti","MESE":12},{"ANNO":2022,"TOTALE":548,"TIPOLOGIA":"ESPATRI","TIPO_SOGGETTO":"Residenti","MESE":12},{"ANNO":2022,"TOTALE":6117,"TIPOLOGIA":"RIENTRI AIRE","TIPO_SOGGETTO":"Residenti","MESE":12},{"ANNO":2022,"TOTALE":108968,"TIPOLOGIA":"STESSA REGIONE","TIPO_SOGGETTO":"Residenti","MESE":12},{"ANNO":2022,"TOTALE":174802,"TIPOLOGIA":"STESSO COMUNE","TIPO_SOGGETTO":"Residenti","MESE":12},{"ANNO":2023,"TOTALE":9500,"TIPOLOGIA":"ESPATRI","TIPO_SOGGETTO":"AIRE","MESE":1},{"ANNO":2023,"TOTALE":23834,"TIPOLOGIA":"ESTERO CON ESTERO","TIPO_SOGGETTO":"AIRE","MESE":1},{"ANNO":2023,"TOTALE":1893,"TIPOLOGIA":"RIENTRI AIRE","TIPO_SOGGETTO":"AIRE","MESE":1},{"ANNO":2023,"TOTALE":42096,"TIPOLOGIA":"DIVERSA REGIONE","TIPO_SOGGETTO":"Residenti","MESE":1},{"ANNO":2023,"TOTALE":724,"TIPOLOGIA":"ESPATRI","TIPO_SOGGETTO":"Residenti","MESE":1},{"ANNO":2023,"TOTALE":7460,"TIPOLOGIA":"RIENTRI AIRE","TIPO_SOGGETTO":"Residenti","MESE":1},{"ANNO":2023,"TOTALE":131168,"TIPOLOGIA":"STESSA REGIONE","TIPO_SOGGETTO":"Residenti","MESE":1},{"ANNO":2023,"TOTALE":188109,"TIPOLOGIA":"STESSO COMUNE","TIPO_SOGGETTO":"Residenti","MESE":1},{"ANNO":2023,"TOTALE":10172,"TIPOLOGIA":"ESPATRI","TIPO_SOGGETTO":"AIRE","MESE":2},{"ANNO":2023,"TOTALE":24480,"TIPOLOGIA":"ESTERO CON ESTERO","TIPO_SOGGETTO":"AIRE","MESE":2},{"ANNO":2023,"TOTALE":1510,"TIPOLOGIA":"RIENTRI AIRE","TIPO_SOGGETTO":"AIRE","MESE":2},{"ANNO":2023,"TOTALE":36092,"TIPOLOGIA":"DIVERSA REGIONE","TIPO_SOGGETTO":"Residenti","MESE":2},{"ANNO":2023,"TOTALE":788,"TIPOLOGIA":"ESPATRI","TIPO_SOGGETTO":"Residenti","MESE":2},{"ANNO":2023,"TOTALE":6885,"TIPOLOGIA":"RIENTRI AIRE","TIPO_SOGGETTO":"Residenti","MESE":2},{"ANNO":2023,"TOTALE":110130,"TIPOLOGIA":"STESSA REGIONE","TIPO_SOGGETTO":"Residenti","MESE":2},{"ANNO":2023,"TOTALE":163049,"TIPOLOGIA":"STESSO COMUNE","TIPO_SOGGETTO":"Residenti","MESE":2},{"ANNO":2023,"TOTALE":11879,"TIPOLOGIA":"ESPATRI","TIPO_SOGGETTO":"AIRE","MESE":3},{"ANNO":2023,"TOTALE":27941,"TIPOLOGIA":"ESTERO CON ESTERO","TIPO_SOGGETTO":"AIRE","MESE":3},{"ANNO":2023,"TOTALE":1712,"TIPOLOGIA":"RIENTRI AIRE","TIPO_SOGGETTO":"AIRE","MESE":3},{"ANNO":2023,"TOTALE":39596,"TIPOLOGIA":"DIVERSA REGIONE","TIPO_SOGGETTO":"Residenti","MESE":3},{"ANNO":2023,"TOTALE":809,"TIPOLOGIA":"ESPATRI","TIPO_SOGGETTO":"Residenti","MESE":3},{"ANNO":2023,"TOTALE":7854,"TIPOLOGIA":"RIENTRI AIRE","TIPO_SOGGETTO":"Residenti","MESE":3},{"ANNO":2023,"TOTALE":124168,"TIPOLOGIA":"STESSA REGIONE","TIPO_SOGGETTO":"Residenti","MESE":3},{"ANNO":2023,"TOTALE":209149,"TIPOLOGIA":"STESSO COMUNE","TIPO_SOGGETTO":"Residenti","MESE":3},{"ANNO":2023,"TOTALE":7705,"TIPOLOGIA":"ESPATRI","TIPO_SOGGETTO":"AIRE","MESE":4},{"ANNO":2023,"TOTALE":20059,"TIPOLOGIA":"ESTERO CON ESTERO","TIPO_SOGGETTO":"AIRE","MESE":4},{"ANNO":2023,"TOTALE":1598,"TIPOLOGIA":"RIENTRI AIRE","TIPO_SOGGETTO":"AIRE","MESE":4},{"ANNO":2023,"TOTALE":29273,"TIPOLOGIA":"DIVERSA REGIONE","TIPO_SOGGETTO":"Residenti","MESE":4},{"ANNO":2023,"TOTALE":537,"TIPOLOGIA":"ESPATRI","TIPO_SOGGETTO":"Residenti","MESE":4},{"ANNO":2023,"TOTALE":6013,"TIPOLOGIA":"RIENTRI AIRE","TIPO_SOGGETTO":"Residenti","MESE":4},{"ANNO":2023,"TOTALE":93565,"TIPOLOGIA":"STESSA REGIONE","TIPO_SOGGETTO":"Residenti","MESE":4},{"ANNO":2023,"TOTALE":131747,"TIPOLOGIA":"STESSO COMUNE","TIPO_SOGGETTO":"Residenti","MESE":4},{"ANNO":2023,"TOTALE":9769,"TIPOLOGIA":"ESPATRI","TIPO_SOGGETTO":"AIRE","MESE":5},{"ANNO":2023,"TOTALE":24890,"TIPOLOGIA":"ESTERO CON ESTERO","TIPO_SOGGETTO":"AIRE","MESE":5},{"ANNO":2023,"TOTALE":1803,"TIPOLOGIA":"RIENTRI AIRE","TIPO_SOGGETTO":"AIRE","MESE":5},{"ANNO":2023,"TOTALE":35829,"TIPOLOGIA":"DIVERSA REGIONE","TIPO_SOGGETTO":"Residenti","MESE":5},{"ANNO":2023,"TOTALE":770,"TIPOLOGIA":"ESPATRI","TIPO_SOGGETTO":"Residenti","MESE":5},{"ANNO":2023,"TOTALE":7627,"TIPOLOGIA":"RIENTRI AIRE","TIPO_SOGGETTO":"Residenti","MESE":5},{"ANNO":2023,"TOTALE":117510,"TIPOLOGIA":"STESSA REGIONE","TIPO_SOGGETTO":"Residenti","MESE":5},{"ANNO":2023,"TOTALE":168029,"TIPOLOGIA":"STESSO COMUNE","TIPO_SOGGETTO":"Residenti","MESE":5},{"ANNO":2023,"TOTALE":8594,"TIPOLOGIA":"ESPATRI","TIPO_SOGGETTO":"AIRE","MESE":6},{"ANNO":2023,"TOTALE":21602,"TIPOLOGIA":"ESTERO CON ESTERO","TIPO_SOGGETTO":"AIRE","MESE":6},{"ANNO":2023,"TOTALE":1953,"TIPOLOGIA":"RIENTRI AIRE","TIPO_SOGGETTO":"AIRE","MESE":6},{"ANNO":2023,"TOTALE":34133,"TIPOLOGIA":"DIVERSA REGIONE","TIPO_SOGGETTO":"Residenti","MESE":6},{"ANNO":2023,"TOTALE":580,"TIPOLOGIA":"ESPATRI","TIPO_SOGGETTO":"Residenti","MESE":6},{"ANNO":2023,"TOTALE":7184,"TIPOLOGIA":"RIENTRI AIRE","TIPO_SOGGETTO":"Residenti","MESE":6},{"ANNO":2023,"TOTALE":113379,"TIPOLOGIA":"STESSA REGIONE","TIPO_SOGGETTO":"Residenti","MESE":6},{"ANNO":2023,"TOTALE":157045,"TIPOLOGIA":"STESSO COMUNE","TIPO_SOGGETTO":"Residenti","MESE":6},{"ANNO":2023,"TOTALE":7086,"TIPOLOGIA":"ESPATRI","TIPO_SOGGETTO":"AIRE","MESE":7},{"ANNO":2023,"TOTALE":19992,"TIPOLOGIA":"ESTERO CON ESTERO","TIPO_SOGGETTO":"AIRE","MESE":7},{"ANNO":2023,"TOTALE":2020,"TIPOLOGIA":"RIENTRI AIRE","TIPO_SOGGETTO":"AIRE","MESE":7},{"ANNO":2023,"TOTALE":36956,"TIPOLOGIA":"DIVERSA REGIONE","TIPO_SOGGETTO":"Residenti","MESE":7},{"ANNO":2023,"TOTALE":541,"TIPOLOGIA":"ESPATRI","TIPO_SOGGETTO":"Residenti","MESE":7},{"ANNO":2023,"TOTALE":7301,"TIPOLOGIA":"RIENTRI AIRE","TIPO_SOGGETTO":"Residenti","MESE":7},{"ANNO":2023,"TOTALE":113645,"TIPOLOGIA":"STESSA REGIONE","TIPO_SOGGETTO":"Residenti","MESE":7},{"ANNO":2023,"TOTALE":147901,"TIPOLOGIA":"STESSO COMUNE","TIPO_SOGGETTO":"Residenti","MESE":7},{"ANNO":2023,"TOTALE":7867,"TIPOLOGIA":"ESPATRI","TIPO_SOGGETTO":"AIRE","MESE":8},{"ANNO":2023,"TOTALE":22714,"TIPOLOGIA":"ESTERO CON ESTERO","TIPO_SOGGETTO":"AIRE","MESE":8},{"ANNO":2023,"TOTALE":2181,"TIPOLOGIA":"RIENTRI AIRE","TIPO_SOGGETTO":"AIRE","MESE":8},{"ANNO":2023,"TOTALE":35355,"TIPOLOGIA":"DIVERSA REGIONE","TIPO_SOGGETTO":"Residenti","MESE":8},{"ANNO":2023,"TOTALE":607,"TIPOLOGIA":"ESPATRI","TIPO_SOGGETTO":"Residenti","MESE":8},{"ANNO":2023,"TOTALE":7139,"TIPOLOGIA":"RIENTRI AIRE","TIPO_SOGGETTO":"Residenti","MESE":8},{"ANNO":2023,"TOTALE":105735,"TIPOLOGIA":"STESSA REGIONE","TIPO_SOGGETTO":"Residenti","MESE":8},{"ANNO":2023,"TOTALE":133829,"TIPOLOGIA":"STESSO COMUNE","TIPO_SOGGETTO":"Residenti","MESE":8},{"ANNO":2023,"TOTALE":8403,"TIPOLOGIA":"ESPATRI","TIPO_SOGGETTO":"AIRE","MESE":9},{"ANNO":2023,"TOTALE":23600,"TIPOLOGIA":"ESTERO CON ESTERO","TIPO_SOGGETTO":"AIRE","MESE":9},{"ANNO":2023,"TOTALE":2202,"TIPOLOGIA":"RIENTRI AIRE","TIPO_SOGGETTO":"AIRE","MESE":9},{"ANNO":2023,"TOTALE":42503,"TIPOLOGIA":"DIVERSA REGIONE","TIPO_SOGGETTO":"Residenti","MESE":9},{"ANNO":2023,"TOTALE":592,"TIPOLOGIA":"ESPATRI","TIPO_SOGGETTO":"Residenti","MESE":9},{"ANNO":2023,"TOTALE":8321,"TIPOLOGIA":"RIENTRI AIRE","TIPO_SOGGETTO":"Residenti","MESE":9},{"ANNO":2023,"TOTALE":112638,"TIPOLOGIA":"STESSA REGIONE","TIPO_SOGGETTO":"Residenti","MESE":9},{"ANNO":2023,"TOTALE":148877,"TIPOLOGIA":"STESSO COMUNE","TIPO_SOGGETTO":"Residenti","MESE":9},{"ANNO":2023,"TOTALE":9514,"TIPOLOGIA":"ESPATRI","TIPO_SOGGETTO":"AIRE","MESE":10},{"ANNO":2023,"TOTALE":26819,"TIPOLOGIA":"ESTERO CON ESTERO","TIPO_SOGGETTO":"AIRE","MESE":10},{"ANNO":2023,"TOTALE":2137,"TIPOLOGIA":"RIENTRI AIRE","TIPO_SOGGETTO":"AIRE","MESE":10},{"ANNO":2023,"TOTALE":43728,"TIPOLOGIA":"DIVERSA REGIONE","TIPO_SOGGETTO":"Residenti","MESE":10},{"ANNO":2023,"TOTALE":683,"TIPOLOGIA":"ESPATRI","TIPO_SOGGETTO":"Residenti","MESE":10},{"ANNO":2023,"TOTALE":8867,"TIPOLOGIA":"RIENTRI AIRE","TIPO_SOGGETTO":"Residenti","MESE":10},{"ANNO":2023,"TOTALE":122448,"TIPOLOGIA":"STESSA REGIONE","TIPO_SOGGETTO":"Residenti","MESE":10},{"ANNO":2023,"TOTALE":169296,"TIPOLOGIA":"STESSO COMUNE","TIPO_SOGGETTO":"Residenti","MESE":10},{"ANNO":2023,"TOTALE":9381,"TIPOLOGIA":"ESPATRI","TIPO_SOGGETTO":"AIRE","MESE":11},{"ANNO":2023,"TOTALE":27026,"TIPOLOGIA":"ESTERO CON ESTERO","TIPO_SOGGETTO":"AIRE","MESE":11},{"ANNO":2023,"TOTALE":1910,"TIPOLOGIA":"RIENTRI AIRE","TIPO_SOGGETTO":"AIRE","MESE":11},{"ANNO":2023,"TOTALE":37575,"TIPOLOGIA":"DIVERSA REGIONE","TIPO_SOGGETTO":"Residenti","MESE":11},{"ANNO":2023,"TOTALE":703,"TIPOLOGIA":"ESPATRI","TIPO_SOGGETTO":"Residenti","MESE":11},{"ANNO":2023,"TOTALE":8008,"TIPOLOGIA":"RIENTRI AIRE","TIPO_SOGGETTO":"Residenti","MESE":11},{"ANNO":2023,"TOTALE":111072,"TIPOLOGIA":"STESSA REGIONE","TIPO_SOGGETTO":"Residenti","MESE":11},{"ANNO":2023,"TOTALE":154525,"TIPOLOGIA":"STESSO COMUNE","TIPO_SOGGETTO":"Residenti","MESE":11},{"ANNO":2023,"TOTALE":7628,"TIPOLOGIA":"ESPATRI","TIPO_SOGGETTO":"AIRE","MESE":12},{"ANNO":2023,"TOTALE":22081,"TIPOLOGIA":"ESTERO CON ESTERO","TIPO_SOGGETTO":"AIRE","MESE":12},{"ANNO":2023,"TOTALE":2220,"TIPOLOGIA":"RIENTRI AIRE","TIPO_SOGGETTO":"AIRE","MESE":12},{"ANNO":2023,"TOTALE":28466,"TIPOLOGIA":"DIVERSA REGIONE","TIPO_SOGGETTO":"Residenti","MESE":12},{"ANNO":2023,"TOTALE":583,"TIPOLOGIA":"ESPATRI","TIPO_SOGGETTO":"Residenti","MESE":12},{"ANNO":2023,"TOTALE":7127,"TIPOLOGIA":"RIENTRI AIRE","TIPO_SOGGETTO":"Residenti","MESE":12},{"ANNO":2023,"TOTALE":95462,"TIPOLOGIA":"STESSA REGIONE","TIPO_SOGGETTO":"Residenti","MESE":12},{"ANNO":2023,"TOTALE":131877,"TIPOLOGIA":"STESSO COMUNE","TIPO_SOGGETTO":"Residenti","MESE":12},{"ANNO":2024,"TOTALE":10562,"TIPOLOGIA":"ESPATRI","TIPO_SOGGETTO":"AIRE","MESE":1},{"ANNO":2024,"TOTALE":25065,"TIPOLOGIA":"ESTERO CON ESTERO","TIPO_SOGGETTO":"AIRE","MESE":1},{"ANNO":2024,"TOTALE":1718,"TIPOLOGIA":"RIENTRI AIRE","TIPO_SOGGETTO":"AIRE","MESE":1},{"ANNO":2024,"TOTALE":41991,"TIPOLOGIA":"DIVERSA REGIONE","TIPO_SOGGETTO":"Residenti","MESE":1},{"ANNO":2024,"TOTALE":922,"TIPOLOGIA":"ESPATRI","TIPO_SOGGETTO":"Residenti","MESE":1},{"ANNO":2024,"TOTALE":7503,"TIPOLOGIA":"RIENTRI AIRE","TIPO_SOGGETTO":"Residenti","MESE":1},{"ANNO":2024,"TOTALE":131792,"TIPOLOGIA":"STESSA REGIONE","TIPO_SOGGETTO":"Residenti","MESE":1},{"ANNO":2024,"TOTALE":191648,"TIPOLOGIA":"STESSO COMUNE","TIPO_SOGGETTO":"Residenti","MESE":1},{"ANNO":2024,"TOTALE":14686,"TIPOLOGIA":"ESPATRI","TIPO_SOGGETTO":"AIRE","MESE":2},{"ANNO":2024,"TOTALE":29889,"TIPOLOGIA":"ESTERO CON ESTERO","TIPO_SOGGETTO":"AIRE","MESE":2},{"ANNO":2024,"TOTALE":1479,"TIPOLOGIA":"RIENTRI AIRE","TIPO_SOGGETTO":"AIRE","MESE":2},{"ANNO":2024,"TOTALE":35823,"TIPOLOGIA":"DIVERSA REGIONE","TIPO_SOGGETTO":"Residenti","MESE":2},{"ANNO":2024,"TOTALE":1166,"TIPOLOGIA":"ESPATRI","TIPO_SOGGETTO":"Residenti","MESE":2},{"ANNO":2024,"TOTALE":6911,"TIPOLOGIA":"RIENTRI AIRE","TIPO_SOGGETTO":"Residenti","MESE":2},{"ANNO":2024,"TOTALE":110847,"TIPOLOGIA":"STESSA REGIONE","TIPO_SOGGETTO":"Residenti","MESE":2},{"ANNO":2024,"TOTALE":164649,"TIPOLOGIA":"STESSO COMUNE","TIPO_SOGGETTO":"Residenti","MESE":2},{"ANNO":2024,"TOTALE":15659,"TIPOLOGIA":"ESPATRI","TIPO_SOGGETTO":"AIRE","MESE":3},{"ANNO":2024,"TOTALE":29731,"TIPOLOGIA":"ESTERO CON ESTERO","TIPO_SOGGETTO":"AIRE","MESE":3},{"ANNO":2024,"TOTALE":1544,"TIPOLOGIA":"RIENTRI AIRE","TIPO_SOGGETTO":"AIRE","MESE":3},{"ANNO":2024,"TOTALE":33443,"TIPOLOGIA":"DIVERSA REGIONE","TIPO_SOGGETTO":"Residenti","MESE":3},{"ANNO":2024,"TOTALE":1104,"TIPOLOGIA":"ESPATRI","TIPO_SOGGETTO":"Residenti","MESE":3},{"ANNO":2024,"TOTALE":6697,"TIPOLOGIA":"RIENTRI AIRE","TIPO_SOGGETTO":"Residenti","MESE":3},{"ANNO":2024,"TOTALE":106881,"TIPOLOGIA":"STESSA REGIONE","TIPO_SOGGETTO":"Residenti","MESE":3},{"ANNO":2024,"TOTALE":151393,"TIPOLOGIA":"STESSO COMUNE","TIPO_SOGGETTO":"Residenti","MESE":3},{"ANNO":2024,"TOTALE":13649,"TIPOLOGIA":"ESPATRI","TIPO_SOGGETTO":"AIRE","MESE":4},{"ANNO":2024,"TOTALE":28651,"TIPOLOGIA":"ESTERO CON ESTERO","TIPO_SOGGETTO":"AIRE","MESE":4},{"ANNO":2024,"TOTALE":1736,"TIPOLOGIA":"RIENTRI AIRE","TIPO_SOGGETTO":"AIRE","MESE":4},{"ANNO":2024,"TOTALE":31052,"TIPOLOGIA":"DIVERSA REGIONE","TIPO_SOGGETTO":"Residenti","MESE":4},{"ANNO":2024,"TOTALE":993,"TIPOLOGIA":"ESPATRI","TIPO_SOGGETTO":"Residenti","MESE":4},{"ANNO":2024,"TOTALE":6388,"TIPOLOGIA":"RIENTRI AIRE","TIPO_SOGGETTO":"Residenti","MESE":4},{"ANNO":2024,"TOTALE":101394,"TIPOLOGIA":"STESSA REGIONE","TIPO_SOGGETTO":"Residenti","MESE":4},{"ANNO":2024,"TOTALE":141407,"TIPOLOGIA":"STESSO COMUNE","TIPO_SOGGETTO":"Residenti","MESE":4},{"ANNO":2024,"TOTALE":11905,"TIPOLOGIA":"ESPATRI","TIPO_SOGGETTO":"AIRE","MESE":5},{"ANNO":2024,"TOTALE":24840,"TIPOLOGIA":"ESTERO CON ESTERO","TIPO_SOGGETTO":"AIRE","MESE":5},{"ANNO":2024,"TOTALE":1756,"TIPOLOGIA":"RIENTRI AIRE","TIPO_SOGGETTO":"AIRE","MESE":5},{"ANNO":2024,"TOTALE":31797,"TIPOLOGIA":"DIVERSA REGIONE","TIPO_SOGGETTO":"Residenti","MESE":5},{"ANNO":2024,"TOTALE":797,"TIPOLOGIA":"ESPATRI","TIPO_SOGGETTO":"Residenti","MESE":5},{"ANNO":2024,"TOTALE":6886,"TIPOLOGIA":"RIENTRI AIRE","TIPO_SOGGETTO":"Residenti","MESE":5},{"ANNO":2024,"TOTALE":108317,"TIPOLOGIA":"STESSA REGIONE","TIPO_SOGGETTO":"Residenti","MESE":5},{"ANNO":2024,"TOTALE":155944,"TIPOLOGIA":"STESSO COMUNE","TIPO_SOGGETTO":"Residenti","MESE":5},{"ANNO":2024,"TOTALE":10423,"TIPOLOGIA":"ESPATRI","TIPO_SOGGETTO":"AIRE","MESE":6},{"ANNO":2024,"TOTALE":24965,"TIPOLOGIA":"ESTERO CON ESTERO","TIPO_SOGGETTO":"AIRE","MESE":6},{"ANNO":2024,"TOTALE":1682,"TIPOLOGIA":"RIENTRI AIRE","TIPO_SOGGETTO":"AIRE","MESE":6},{"ANNO":2024,"TOTALE":30024,"TIPOLOGIA":"DIVERSA REGIONE","TIPO_SOGGETTO":"Residenti","MESE":6},{"ANNO":2024,"TOTALE":797,"TIPOLOGIA":"ESPATRI","TIPO_SOGGETTO":"Residenti","MESE":6},{"ANNO":2024,"TOTALE":6181,"TIPOLOGIA":"RIENTRI AIRE","TIPO_SOGGETTO":"Residenti","MESE":6},{"ANNO":2024,"TOTALE":102931,"TIPOLOGIA":"STESSA REGIONE","TIPO_SOGGETTO":"Residenti","MESE":6},{"ANNO":2024,"TOTALE":136287,"TIPOLOGIA":"STESSO COMUNE","TIPO_SOGGETTO":"Residenti","MESE":6},{"ANNO":2024,"TOTALE":12565,"TIPOLOGIA":"ESPATRI","TIPO_SOGGETTO":"AIRE","MESE":7},{"ANNO":2024,"TOTALE":28705,"TIPOLOGIA":"ESTERO CON ESTERO","TIPO_SOGGETTO":"AIRE","MESE":7},{"ANNO":2024,"TOTALE":2249,"TIPOLOGIA":"RIENTRI AIRE","TIPO_SOGGETTO":"AIRE","MESE":7},{"ANNO":2024,"TOTALE":37540,"TIPOLOGIA":"DIVERSA REGIONE","TIPO_SOGGETTO":"Residenti","MESE":7},{"ANNO":2024,"TOTALE":953,"TIPOLOGIA":"ESPATRI","TIPO_SOGGETTO":"Residenti","MESE":7},{"ANNO":2024,"TOTALE":7564,"TIPOLOGIA":"RIENTRI AIRE","TIPO_SOGGETTO":"Residenti","MESE":7},{"ANNO":2024,"TOTALE":119521,"TIPOLOGIA":"STESSA REGIONE","TIPO_SOGGETTO":"Residenti","MESE":7},{"ANNO":2024,"TOTALE":155683,"TIPOLOGIA":"STESSO COMUNE","TIPO_SOGGETTO":"Residenti","MESE":7},{"ANNO":2024,"TOTALE":9346,"TIPOLOGIA":"ESPATRI","TIPO_SOGGETTO":"AIRE","MESE":8},{"ANNO":2024,"TOTALE":24904,"TIPOLOGIA":"ESTERO CON ESTERO","TIPO_SOGGETTO":"AIRE","MESE":8},{"ANNO":2024,"TOTALE":1926,"TIPOLOGIA":"RIENTRI AIRE","TIPO_SOGGETTO":"AIRE","MESE":8},{"ANNO":2024,"TOTALE":31018,"TIPOLOGIA":"DIVERSA REGIONE","TIPO_SOGGETTO":"Residenti","MESE":8},{"ANNO":2024,"TOTALE":700,"TIPOLOGIA":"ESPATRI","TIPO_SOGGETTO":"Residenti","MESE":8},{"ANNO":2024,"TOTALE":6520,"TIPOLOGIA":"RIENTRI AIRE","TIPO_SOGGETTO":"Residenti","MESE":8},{"ANNO":2024,"TOTALE":95236,"TIPOLOGIA":"STESSA REGIONE","TIPO_SOGGETTO":"Residenti","MESE":8},{"ANNO":2024,"TOTALE":117531,"TIPOLOGIA":"STESSO COMUNE","TIPO_SOGGETTO":"Residenti","MESE":8},{"ANNO":2024,"TOTALE":9820,"TIPOLOGIA":"ESPATRI","TIPO_SOGGETTO":"AIRE","MESE":9},{"ANNO":2024,"TOTALE":27120,"TIPOLOGIA":"ESTERO CON ESTERO","TIPO_SOGGETTO":"AIRE","MESE":9},{"ANNO":2024,"TOTALE":2233,"TIPOLOGIA":"RIENTRI AIRE","TIPO_SOGGETTO":"AIRE","MESE":9},{"ANNO":2024,"TOTALE":40661,"TIPOLOGIA":"DIVERSA REGIONE","TIPO_SOGGETTO":"Residenti","MESE":9},{"ANNO":2024,"TOTALE":793,"TIPOLOGIA":"ESPATRI","TIPO_SOGGETTO":"Residenti","MESE":9},{"ANNO":2024,"TOTALE":7998,"TIPOLOGIA":"RIENTRI AIRE","TIPO_SOGGETTO":"Residenti","MESE":9},{"ANNO":2024,"TOTALE":108389,"TIPOLOGIA":"STESSA REGIONE","TIPO_SOGGETTO":"Residenti","MESE":9},{"ANNO":2024,"TOTALE":143493,"TIPOLOGIA":"STESSO COMUNE","TIPO_SOGGETTO":"Residenti","MESE":9},{"ANNO":2024,"TOTALE":12092,"TIPOLOGIA":"ESPATRI","TIPO_SOGGETTO":"AIRE","MESE":10},{"ANNO":2024,"TOTALE":31604,"TIPOLOGIA":"ESTERO CON ESTERO","TIPO_SOGGETTO":"AIRE","MESE":10},{"ANNO":2024,"TOTALE":2156,"TIPOLOGIA":"RIENTRI AIRE","TIPO_SOGGETTO":"AIRE","MESE":10},{"ANNO":2024,"TOTALE":42496,"TIPOLOGIA":"DIVERSA REGIONE","TIPO_SOGGETTO":"Residenti","MESE":10},{"ANNO":2024,"TOTALE":879,"TIPOLOGIA":"ESPATRI","TIPO_SOGGETTO":"Residenti","MESE":10},{"ANNO":2024,"TOTALE":8444,"TIPOLOGIA":"RIENTRI AIRE","TIPO_SOGGETTO":"Residenti","MESE":10},{"ANNO":2024,"TOTALE":124055,"TIPOLOGIA":"STESSA REGIONE","TIPO_SOGGETTO":"Residenti","MESE":10},{"ANNO":2024,"TOTALE":171952,"TIPOLOGIA":"STESSO COMUNE","TIPO_SOGGETTO":"Residenti","MESE":10},{"ANNO":2024,"TOTALE":10437,"TIPOLOGIA":"ESPATRI","TIPO_SOGGETTO":"AIRE","MESE":11},{"ANNO":2024,"TOTALE":26751,"TIPOLOGIA":"ESTERO CON ESTERO","TIPO_SOGGETTO":"AIRE","MESE":11},{"ANNO":2024,"TOTALE":1616,"TIPOLOGIA":"RIENTRI AIRE","TIPO_SOGGETTO":"AIRE","MESE":11},{"ANNO":2024,"TOTALE":33468,"TIPOLOGIA":"DIVERSA REGIONE","TIPO_SOGGETTO":"Residenti","MESE":11},{"ANNO":2024,"TOTALE":846,"TIPOLOGIA":"ESPATRI","TIPO_SOGGETTO":"Residenti","MESE":11},{"ANNO":2024,"TOTALE":6715,"TIPOLOGIA":"RIENTRI AIRE","TIPO_SOGGETTO":"Residenti","MESE":11},{"ANNO":2024,"TOTALE":105213,"TIPOLOGIA":"STESSA REGIONE","TIPO_SOGGETTO":"Residenti","MESE":11},{"ANNO":2024,"TOTALE":144953,"TIPOLOGIA":"STESSO COMUNE","TIPO_SOGGETTO":"Residenti","MESE":11},{"ANNO":2024,"TOTALE":8691,"TIPOLOGIA":"ESPATRI","TIPO_SOGGETTO":"AIRE","MESE":12},{"ANNO":2024,"TOTALE":23245,"TIPOLOGIA":"ESTERO CON ESTERO","TIPO_SOGGETTO":"AIRE","MESE":12},{"ANNO":2024,"TOTALE":1689,"TIPOLOGIA":"RIENTRI AIRE","TIPO_SOGGETTO":"AIRE","MESE":12},{"ANNO":2024,"TOTALE":29667,"TIPOLOGIA":"DIVERSA REGIONE","TIPO_SOGGETTO":"Residenti","MESE":12},{"ANNO":2024,"TOTALE":711,"TIPOLOGIA":"ESPATRI","TIPO_SOGGETTO":"Residenti","MESE":12},{"ANNO":2024,"TOTALE":5660,"TIPOLOGIA":"RIENTRI AIRE","TIPO_SOGGETTO":"Residenti","MESE":12},{"ANNO":2024,"TOTALE":104862,"TIPOLOGIA":"STESSA REGIONE","TIPO_SOGGETTO":"Residenti","MESE":12},{"ANNO":2024,"TOTALE":144887,"TIPOLOGIA":"STESSO COMUNE","TIPO_SOGGETTO":"Residenti","MESE":12},{"ANNO":2025,"TOTALE":9547,"TIPOLOGIA":"ESPATRI","TIPO_SOGGETTO":"AIRE","MESE":1},{"ANNO":2025,"TOTALE":24296,"TIPOLOGIA":"ESTERO CON ESTERO","TIPO_SOGGETTO":"AIRE","MESE":1},{"ANNO":2025,"TOTALE":1976,"TIPOLOGIA":"RIENTRI AIRE","TIPO_SOGGETTO":"AIRE","MESE":1},{"ANNO":2025,"TOTALE":38969,"TIPOLOGIA":"DIVERSA REGIONE","TIPO_SOGGETTO":"Residenti","MESE":1},{"ANNO":2025,"TOTALE":700,"TIPOLOGIA":"ESPATRI","TIPO_SOGGETTO":"Residenti","MESE":1},{"ANNO":2025,"TOTALE":7120,"TIPOLOGIA":"RIENTRI AIRE","TIPO_SOGGETTO":"Residenti","MESE":1},{"ANNO":2025,"TOTALE":125471,"TIPOLOGIA":"STESSA REGIONE","TIPO_SOGGETTO":"Residenti","MESE":1},{"ANNO":2025,"TOTALE":175921,"TIPOLOGIA":"STESSO COMUNE","TIPO_SOGGETTO":"Residenti","MESE":1},{"ANNO":2025,"TOTALE":10492,"TIPOLOGIA":"ESPATRI","TIPO_SOGGETTO":"AIRE","MESE":2},{"ANNO":2025,"TOTALE":28539,"TIPOLOGIA":"ESTERO CON ESTERO","TIPO_SOGGETTO":"AIRE","MESE":2},{"ANNO":2025,"TOTALE":1633,"TIPOLOGIA":"RIENTRI AIRE","TIPO_SOGGETTO":"AIRE","MESE":2},{"ANNO":2025,"TOTALE":34090,"TIPOLOGIA":"DIVERSA REGIONE","TIPO_SOGGETTO":"Residenti","MESE":2},{"ANNO":2025,"TOTALE":746,"TIPOLOGIA":"ESPATRI","TIPO_SOGGETTO":"Residenti","MESE":2},{"ANNO":2025,"TOTALE":6535,"TIPOLOGIA":"RIENTRI AIRE","TIPO_SOGGETTO":"Residenti","MESE":2},{"ANNO":2025,"TOTALE":109225,"TIPOLOGIA":"STESSA REGIONE","TIPO_SOGGETTO":"Residenti","MESE":2},{"ANNO":2025,"TOTALE":159078,"TIPOLOGIA":"STESSO COMUNE","TIPO_SOGGETTO":"Residenti","MESE":2}]