[{"ANNO":2021,"VISURE":535,"AUTOCERTIFICAZIONI":150,"TOTALE":686,"TIPO SOGGETTO":"AIRE","MESE":4},{"ANNO":2021,"VISURE":33635,"AUTOCERTIFICAZIONI":14337,"TOTALE":47992,"TIPO SOGGETTO":"Residenti","MESE":4},{"ANNO":2021,"VISURE":434,"AUTOCERTIFICAZIONI":148,"TOTALE":582,"TIPO SOGGETTO":"AIRE","MESE":5},{"ANNO":2021,"VISURE":25995,"AUTOCERTIFICAZIONI":12155,"TOTALE":38164,"TIPO SOGGETTO":"Residenti","MESE":5},{"ANNO":2021,"VISURE":420,"AUTOCERTIFICAZIONI":109,"TOTALE":539,"TIPO SOGGETTO":"AIRE","MESE":6},{"ANNO":2021,"VISURE":26953,"AUTOCERTIFICAZIONI":11664,"TOTALE":38709,"TIPO SOGGETTO":"Residenti","MESE":6},{"ANNO":2021,"VISURE":410,"AUTOCERTIFICAZIONI":131,"TOTALE":551,"TIPO SOGGETTO":"AIRE","MESE":7},{"ANNO":2021,"VISURE":23031,"AUTOCERTIFICAZIONI":10286,"TOTALE":33511,"TIPO SOGGETTO":"Residenti","MESE":7},{"ANNO":2021,"VISURE":336,"AUTOCERTIFICAZIONI":134,"TOTALE":478,"TIPO SOGGETTO":"AIRE","MESE":8},{"ANNO":2021,"VISURE":18057,"AUTOCERTIFICAZIONI":7719,"TOTALE":25956,"TIPO SOGGETTO":"Residenti","MESE":8},{"ANNO":2021,"VISURE":338,"AUTOCERTIFICAZIONI":97,"TOTALE":453,"TIPO SOGGETTO":"AIRE","MESE":9},{"ANNO":2021,"VISURE":29743,"AUTOCERTIFICAZIONI":13610,"TOTALE":43602,"TIPO SOGGETTO":"Residenti","MESE":9},{"ANNO":2021,"VISURE":897,"AUTOCERTIFICAZIONI":265,"TOTALE":1202,"TIPO SOGGETTO":"AIRE","MESE":10},{"ANNO":2021,"VISURE":66951,"AUTOCERTIFICAZIONI":28934,"TOTALE":96422,"TIPO SOGGETTO":"Residenti","MESE":10},{"ANNO":2021,"VISURE":11256,"AUTOCERTIFICAZIONI":2426,"TOTALE":19945,"TIPO SOGGETTO":"AIRE","MESE":11},{"ANNO":2021,"VISURE":814974,"AUTOCERTIFICAZIONI":199165,"TOTALE":1493438,"TIPO SOGGETTO":"Residenti","MESE":11},{"ANNO":2021,"VISURE":4174,"AUTOCERTIFICAZIONI":843,"TOTALE":8387,"TIPO SOGGETTO":"AIRE","MESE":12},{"ANNO":2021,"VISURE":209895,"AUTOCERTIFICAZIONI":47095,"TOTALE":558422,"TIPO SOGGETTO":"Residenti","MESE":12},{"ANNO":2022,"VISURE":4644,"AUTOCERTIFICAZIONI":822,"TOTALE":8525,"TIPO SOGGETTO":"AIRE","MESE":1},{"ANNO":2022,"VISURE":270227,"AUTOCERTIFICAZIONI":65353,"TOTALE":720521,"TIPO SOGGETTO":"Residenti","MESE":1},{"ANNO":2022,"VISURE":3959,"AUTOCERTIFICAZIONI":779,"TOTALE":7589,"TIPO SOGGETTO":"AIRE","MESE":2},{"ANNO":2022,"VISURE":227767,"AUTOCERTIFICAZIONI":54318,"TOTALE":634803,"TIPO SOGGETTO":"Residenti","MESE":2},{"ANNO":2022,"VISURE":3759,"AUTOCERTIFICAZIONI":864,"TOTALE":7467,"TIPO SOGGETTO":"AIRE","MESE":3},{"ANNO":2022,"VISURE":218789,"AUTOCERTIFICAZIONI":53471,"TOTALE":642911,"TIPO SOGGETTO":"Residenti","MESE":3},{"ANNO":2022,"VISURE":3817,"AUTOCERTIFICAZIONI":801,"TOTALE":7453,"TIPO SOGGETTO":"AIRE","MESE":4},{"ANNO":2022,"VISURE":187781,"AUTOCERTIFICAZIONI":42496,"TOTALE":531667,"TIPO SOGGETTO":"Residenti","MESE":4},{"ANNO":2022,"VISURE":4093,"AUTOCERTIFICAZIONI":768,"TOTALE":8016,"TIPO SOGGETTO":"AIRE","MESE":5},{"ANNO":2022,"VISURE":215790,"AUTOCERTIFICAZIONI":48255,"TOTALE":623418,"TIPO SOGGETTO":"Residenti","MESE":5},{"ANNO":2022,"VISURE":3719,"AUTOCERTIFICAZIONI":781,"TOTALE":7283,"TIPO SOGGETTO":"AIRE","MESE":6},{"ANNO":2022,"VISURE":193003,"AUTOCERTIFICAZIONI":44064,"TOTALE":572826,"TIPO SOGGETTO":"Residenti","MESE":6},{"ANNO":2022,"VISURE":3669,"AUTOCERTIFICAZIONI":698,"TOTALE":7082,"TIPO SOGGETTO":"AIRE","MESE":7},{"ANNO":2022,"VISURE":192816,"AUTOCERTIFICAZIONI":40477,"TOTALE":554792,"TIPO SOGGETTO":"Residenti","MESE":7},{"ANNO":2022,"VISURE":3684,"AUTOCERTIFICAZIONI":764,"TOTALE":7254,"TIPO SOGGETTO":"AIRE","MESE":8},{"ANNO":2022,"VISURE":163050,"AUTOCERTIFICAZIONI":32690,"TOTALE":446873,"TIPO SOGGETTO":"Residenti","MESE":8},{"ANNO":2022,"VISURE":3996,"AUTOCERTIFICAZIONI":790,"TOTALE":7751,"TIPO SOGGETTO":"AIRE","MESE":9},{"ANNO":2022,"VISURE":234439,"AUTOCERTIFICAZIONI":50388,"TOTALE":730905,"TIPO SOGGETTO":"Residenti","MESE":9},{"ANNO":2022,"VISURE":4235,"AUTOCERTIFICAZIONI":853,"TOTALE":8153,"TIPO SOGGETTO":"AIRE","MESE":10},{"ANNO":2022,"VISURE":233925,"AUTOCERTIFICAZIONI":49246,"TOTALE":705022,"TIPO SOGGETTO":"Residenti","MESE":10},{"ANNO":2022,"VISURE":4243,"AUTOCERTIFICAZIONI":881,"TOTALE":8234,"TIPO SOGGETTO":"AIRE","MESE":11},{"ANNO":2022,"VISURE":227523,"AUTOCERTIFICAZIONI":48118,"TOTALE":666252,"TIPO SOGGETTO":"Residenti","MESE":11},{"ANNO":2022,"VISURE":4120,"AUTOCERTIFICAZIONI":827,"TOTALE":8137,"TIPO SOGGETTO":"AIRE","MESE":12},{"ANNO":2022,"VISURE":193629,"AUTOCERTIFICAZIONI":40635,"TOTALE":557950,"TIPO SOGGETTO":"Residenti","MESE":12},{"ANNO":2023,"VISURE":5428,"AUTOCERTIFICAZIONI":1167,"TOTALE":10171,"TIPO SOGGETTO":"AIRE","MESE":1},{"ANNO":2023,"VISURE":307510,"AUTOCERTIFICAZIONI":69913,"TOTALE":829220,"TIPO SOGGETTO":"Residenti","MESE":1},{"ANNO":2023,"VISURE":4773,"AUTOCERTIFICAZIONI":1170,"TOTALE":9085,"TIPO SOGGETTO":"AIRE","MESE":2},{"ANNO":2023,"VISURE":253851,"AUTOCERTIFICAZIONI":59796,"TOTALE":700359,"TIPO SOGGETTO":"Residenti","MESE":2},{"ANNO":2023,"VISURE":5771,"AUTOCERTIFICAZIONI":1414,"TOTALE":10559,"TIPO SOGGETTO":"AIRE","MESE":3},{"ANNO":2023,"VISURE":309648,"AUTOCERTIFICAZIONI":82171,"TOTALE":765410,"TIPO SOGGETTO":"Residenti","MESE":3},{"ANNO":2023,"VISURE":5336,"AUTOCERTIFICAZIONI":1342,"TOTALE":9365,"TIPO SOGGETTO":"AIRE","MESE":4},{"ANNO":2023,"VISURE":270775,"AUTOCERTIFICAZIONI":74220,"TOTALE":623677,"TIPO SOGGETTO":"Residenti","MESE":4},{"ANNO":2023,"VISURE":5891,"AUTOCERTIFICAZIONI":1475,"TOTALE":10242,"TIPO SOGGETTO":"AIRE","MESE":5},{"ANNO":2023,"VISURE":326476,"AUTOCERTIFICAZIONI":91752,"TOTALE":758313,"TIPO SOGGETTO":"Residenti","MESE":5},{"ANNO":2023,"VISURE":5436,"AUTOCERTIFICAZIONI":1340,"TOTALE":9384,"TIPO SOGGETTO":"AIRE","MESE":6},{"ANNO":2023,"VISURE":287799,"AUTOCERTIFICAZIONI":80262,"TOTALE":671144,"TIPO SOGGETTO":"Residenti","MESE":6},{"ANNO":2023,"VISURE":5141,"AUTOCERTIFICAZIONI":1304,"TOTALE":9085,"TIPO SOGGETTO":"AIRE","MESE":7},{"ANNO":2023,"VISURE":276095,"AUTOCERTIFICAZIONI":76090,"TOTALE":674422,"TIPO SOGGETTO":"Residenti","MESE":7},{"ANNO":2023,"VISURE":4961,"AUTOCERTIFICAZIONI":1081,"TOTALE":8420,"TIPO SOGGETTO":"AIRE","MESE":8},{"ANNO":2023,"VISURE":219290,"AUTOCERTIFICAZIONI":55339,"TOTALE":528903,"TIPO SOGGETTO":"Residenti","MESE":8},{"ANNO":2023,"VISURE":5459,"AUTOCERTIFICAZIONI":1396,"TOTALE":9523,"TIPO SOGGETTO":"AIRE","MESE":9},{"ANNO":2023,"VISURE":306058,"AUTOCERTIFICAZIONI":82156,"TOTALE":820269,"TIPO SOGGETTO":"Residenti","MESE":9},{"ANNO":2023,"VISURE":6109,"AUTOCERTIFICAZIONI":1397,"TOTALE":10379,"TIPO SOGGETTO":"AIRE","MESE":10},{"ANNO":2023,"VISURE":315610,"AUTOCERTIFICAZIONI":81112,"TOTALE":800914,"TIPO SOGGETTO":"Residenti","MESE":10},{"ANNO":2023,"VISURE":5851,"AUTOCERTIFICAZIONI":1381,"TOTALE":9943,"TIPO SOGGETTO":"AIRE","MESE":11},{"ANNO":2023,"VISURE":292865,"AUTOCERTIFICAZIONI":75303,"TOTALE":706288,"TIPO SOGGETTO":"Residenti","MESE":11},{"ANNO":2023,"VISURE":5589,"AUTOCERTIFICAZIONI":1382,"TOTALE":9532,"TIPO SOGGETTO":"AIRE","MESE":12},{"ANNO":2023,"VISURE":258272,"AUTOCERTIFICAZIONI":61784,"TOTALE":669894,"TIPO SOGGETTO":"Residenti","MESE":12},{"ANNO":2024,"VISURE":7244,"AUTOCERTIFICAZIONI":1762,"TOTALE":12345,"TIPO SOGGETTO":"AIRE","MESE":1},{"ANNO":2024,"VISURE":402015,"AUTOCERTIFICAZIONI":111353,"TOTALE":1151406,"TIPO SOGGETTO":"Residenti","MESE":1},{"ANNO":2024,"VISURE":7397,"AUTOCERTIFICAZIONI":1588,"TOTALE":12497,"TIPO SOGGETTO":"AIRE","MESE":2},{"ANNO":2024,"VISURE":364027,"AUTOCERTIFICAZIONI":98304,"TOTALE":1109261,"TIPO SOGGETTO":"Residenti","MESE":2},{"ANNO":2024,"VISURE":7193,"AUTOCERTIFICAZIONI":1701,"TOTALE":12740,"TIPO SOGGETTO":"AIRE","MESE":3},{"ANNO":2024,"VISURE":337694,"AUTOCERTIFICAZIONI":96314,"TOTALE":1080533,"TIPO SOGGETTO":"Residenti","MESE":3},{"ANNO":2024,"VISURE":7010,"AUTOCERTIFICAZIONI":1704,"TOTALE":12459,"TIPO SOGGETTO":"AIRE","MESE":4},{"ANNO":2024,"VISURE":310131,"AUTOCERTIFICAZIONI":87768,"TOTALE":1020220,"TIPO SOGGETTO":"Residenti","MESE":4},{"ANNO":2024,"VISURE":7604,"AUTOCERTIFICAZIONI":1820,"TOTALE":13292,"TIPO SOGGETTO":"AIRE","MESE":5},{"ANNO":2024,"VISURE":352392,"AUTOCERTIFICAZIONI":99457,"TOTALE":1162468,"TIPO SOGGETTO":"Residenti","MESE":5},{"ANNO":2024,"VISURE":7110,"AUTOCERTIFICAZIONI":1628,"TOTALE":12216,"TIPO SOGGETTO":"AIRE","MESE":6},{"ANNO":2024,"VISURE":313065,"AUTOCERTIFICAZIONI":86347,"TOTALE":1019824,"TIPO SOGGETTO":"Residenti","MESE":6},{"ANNO":2024,"VISURE":7003,"AUTOCERTIFICAZIONI":1630,"TOTALE":12206,"TIPO SOGGETTO":"AIRE","MESE":7},{"ANNO":2024,"VISURE":314418,"AUTOCERTIFICAZIONI":86303,"TOTALE":1097625,"TIPO SOGGETTO":"Residenti","MESE":7},{"ANNO":2024,"VISURE":5985,"AUTOCERTIFICAZIONI":1207,"TOTALE":9973,"TIPO SOGGETTO":"AIRE","MESE":8},{"ANNO":2024,"VISURE":216483,"AUTOCERTIFICAZIONI":56691,"TOTALE":645752,"TIPO SOGGETTO":"Residenti","MESE":8}]