[{"ANNO":2021,"VISURE":535,"AUTOCERTIFICAZIONI":150,"TOTALE":687,"TIPO SOGGETTO":"AIRE","MESE":4},{"ANNO":2021,"VISURE":33601,"AUTOCERTIFICAZIONI":14327,"TOTALE":48011,"TIPO SOGGETTO":"Residenti","MESE":4},{"ANNO":2021,"VISURE":434,"AUTOCERTIFICAZIONI":148,"TOTALE":584,"TIPO SOGGETTO":"AIRE","MESE":5},{"ANNO":2021,"VISURE":25969,"AUTOCERTIFICAZIONI":12145,"TOTALE":38176,"TIPO SOGGETTO":"Residenti","MESE":5},{"ANNO":2021,"VISURE":419,"AUTOCERTIFICAZIONI":109,"TOTALE":557,"TIPO SOGGETTO":"AIRE","MESE":6},{"ANNO":2021,"VISURE":26915,"AUTOCERTIFICAZIONI":11647,"TOTALE":39045,"TIPO SOGGETTO":"Residenti","MESE":6},{"ANNO":2021,"VISURE":409,"AUTOCERTIFICAZIONI":130,"TOTALE":569,"TIPO SOGGETTO":"AIRE","MESE":7},{"ANNO":2021,"VISURE":22989,"AUTOCERTIFICAZIONI":10270,"TOTALE":34136,"TIPO SOGGETTO":"Residenti","MESE":7},{"ANNO":2021,"VISURE":334,"AUTOCERTIFICAZIONI":133,"TOTALE":493,"TIPO SOGGETTO":"AIRE","MESE":8},{"ANNO":2021,"VISURE":18049,"AUTOCERTIFICAZIONI":7714,"TOTALE":26513,"TIPO SOGGETTO":"Residenti","MESE":8},{"ANNO":2021,"VISURE":338,"AUTOCERTIFICAZIONI":97,"TOTALE":474,"TIPO SOGGETTO":"AIRE","MESE":9},{"ANNO":2021,"VISURE":29721,"AUTOCERTIFICAZIONI":13607,"TOTALE":44520,"TIPO SOGGETTO":"Residenti","MESE":9},{"ANNO":2021,"VISURE":887,"AUTOCERTIFICAZIONI":264,"TOTALE":1250,"TIPO SOGGETTO":"AIRE","MESE":10},{"ANNO":2021,"VISURE":66875,"AUTOCERTIFICAZIONI":28904,"TOTALE":98312,"TIPO SOGGETTO":"Residenti","MESE":10},{"ANNO":2021,"VISURE":11162,"AUTOCERTIFICAZIONI":2418,"TOTALE":20568,"TIPO SOGGETTO":"AIRE","MESE":11},{"ANNO":2021,"VISURE":814215,"AUTOCERTIFICAZIONI":198984,"TOTALE":1512556,"TIPO SOGGETTO":"Residenti","MESE":11},{"ANNO":2021,"VISURE":4121,"AUTOCERTIFICAZIONI":836,"TOTALE":8545,"TIPO SOGGETTO":"AIRE","MESE":12},{"ANNO":2021,"VISURE":209588,"AUTOCERTIFICAZIONI":47053,"TOTALE":564147,"TIPO SOGGETTO":"Residenti","MESE":12},{"ANNO":2022,"VISURE":4608,"AUTOCERTIFICAZIONI":818,"TOTALE":8751,"TIPO SOGGETTO":"AIRE","MESE":1},{"ANNO":2022,"VISURE":269763,"AUTOCERTIFICAZIONI":65258,"TOTALE":728330,"TIPO SOGGETTO":"Residenti","MESE":1},{"ANNO":2022,"VISURE":3920,"AUTOCERTIFICAZIONI":774,"TOTALE":8107,"TIPO SOGGETTO":"AIRE","MESE":2},{"ANNO":2022,"VISURE":227422,"AUTOCERTIFICAZIONI":54257,"TOTALE":660867,"TIPO SOGGETTO":"Residenti","MESE":2},{"ANNO":2022,"VISURE":3731,"AUTOCERTIFICAZIONI":862,"TOTALE":7891,"TIPO SOGGETTO":"AIRE","MESE":3},{"ANNO":2022,"VISURE":218374,"AUTOCERTIFICAZIONI":53387,"TOTALE":667175,"TIPO SOGGETTO":"Residenti","MESE":3},{"ANNO":2022,"VISURE":3731,"AUTOCERTIFICAZIONI":792,"TOTALE":7932,"TIPO SOGGETTO":"AIRE","MESE":4},{"ANNO":2022,"VISURE":187448,"AUTOCERTIFICAZIONI":42450,"TOTALE":555897,"TIPO SOGGETTO":"Residenti","MESE":4},{"ANNO":2022,"VISURE":3983,"AUTOCERTIFICAZIONI":759,"TOTALE":8437,"TIPO SOGGETTO":"AIRE","MESE":5},{"ANNO":2022,"VISURE":215379,"AUTOCERTIFICAZIONI":48191,"TOTALE":658454,"TIPO SOGGETTO":"Residenti","MESE":5},{"ANNO":2022,"VISURE":3682,"AUTOCERTIFICAZIONI":773,"TOTALE":7722,"TIPO SOGGETTO":"AIRE","MESE":6},{"ANNO":2022,"VISURE":192629,"AUTOCERTIFICAZIONI":44008,"TOTALE":604122,"TIPO SOGGETTO":"Residenti","MESE":6},{"ANNO":2022,"VISURE":3609,"AUTOCERTIFICAZIONI":691,"TOTALE":7494,"TIPO SOGGETTO":"AIRE","MESE":7},{"ANNO":2022,"VISURE":192376,"AUTOCERTIFICAZIONI":40406,"TOTALE":587033,"TIPO SOGGETTO":"Residenti","MESE":7},{"ANNO":2022,"VISURE":3607,"AUTOCERTIFICAZIONI":758,"TOTALE":7623,"TIPO SOGGETTO":"AIRE","MESE":8},{"ANNO":2022,"VISURE":162639,"AUTOCERTIFICAZIONI":32653,"TOTALE":475310,"TIPO SOGGETTO":"Residenti","MESE":8},{"ANNO":2022,"VISURE":3906,"AUTOCERTIFICAZIONI":777,"TOTALE":8179,"TIPO SOGGETTO":"AIRE","MESE":9},{"ANNO":2022,"VISURE":233941,"AUTOCERTIFICAZIONI":50311,"TOTALE":768896,"TIPO SOGGETTO":"Residenti","MESE":9},{"ANNO":2022,"VISURE":4138,"AUTOCERTIFICAZIONI":839,"TOTALE":8461,"TIPO SOGGETTO":"AIRE","MESE":10},{"ANNO":2022,"VISURE":233575,"AUTOCERTIFICAZIONI":49180,"TOTALE":744833,"TIPO SOGGETTO":"Residenti","MESE":10},{"ANNO":2022,"VISURE":4178,"AUTOCERTIFICAZIONI":866,"TOTALE":8565,"TIPO SOGGETTO":"AIRE","MESE":11},{"ANNO":2022,"VISURE":227197,"AUTOCERTIFICAZIONI":48077,"TOTALE":705251,"TIPO SOGGETTO":"Residenti","MESE":11},{"ANNO":2022,"VISURE":4025,"AUTOCERTIFICAZIONI":804,"TOTALE":8442,"TIPO SOGGETTO":"AIRE","MESE":12},{"ANNO":2022,"VISURE":193323,"AUTOCERTIFICAZIONI":40581,"TOTALE":591838,"TIPO SOGGETTO":"Residenti","MESE":12},{"ANNO":2023,"VISURE":5219,"AUTOCERTIFICAZIONI":1113,"TOTALE":10677,"TIPO SOGGETTO":"AIRE","MESE":1},{"ANNO":2023,"VISURE":307231,"AUTOCERTIFICAZIONI":69908,"TOTALE":891474,"TIPO SOGGETTO":"Residenti","MESE":1}]